{"cameraMode":{"drawMode":0,"name":"Shaded","section":"Shading Mode"},"sceneLighting":true,"audioPlay":false,"sceneViewState":{"m_AlwaysRefresh":false,"showFog":true,"showSkybox":true,"showFlares":true,"showImageEffects":true,"showParticleSystems":true,"showVisualEffectGraphs":true,"m_FxEnabled":true},"in2DMode":false,"pivot":{"x":-0.8927513957023621,"y":6.300739765167236,"z":-11.244718551635743},"rotation":{"x":-0.2184261828660965,"y":0.4839971661567688,"z":-0.12616588175296784,"w":-0.8379263877868652},"size":21.339611053466798,"orthographic":true}